{"BTC_WETH_3000": {"0xa0Ee7A142d267C1f36714E4a8F75612F20a79720": [{"tick_lower": 29460, "tick_upper": 30420, "liquidity": 2357459552964517036032, "amount_token1": 500.0}, {"tick_lower": 28920, "tick_upper": 30900, "liquidity": 1157633112279135551488, "amount_token1": 500.0}, {"tick_lower": 28320, "tick_upper": 31380, "liquidity": 759226228836920983552, "amount_token1": 500.0}, {"tick_lower": 27720, "tick_upper": 31800, "liquidity": 576774577084051619840, "amount_token1": 500.0}, {"tick_lower": 27060, "tick_upper": 32220, "liquidity": 462346405421425950720, "amount_token1": 500.0}, {"tick_lower": 26400, "tick_upper": 32580, "liquidity": 391154874393450708992, "amount_token1": 500.0}, {"tick_lower": 25680, "tick_upper": 32940, "liquidity": 337702550620015886336, "amount_token1": 500.0}, {"tick_lower": 24840, "tick_upper": 33300, "liquidity": 294494053684851998720, "amount_token1": 500.0}, {"tick_lower": 24000, "tick_upper": 33660, "liquidity": 262091923324847194112, "amount_token1": 500.0}, {"tick_lower": 23040, "tick_upper": 34020, "liquidity": 234784829113368477696, "amount_token1": 500.0}, {"tick_lower": 21960, "tick_upper": 34320, "liquidity": 212739943712049233920, "amount_token1": 500.0}, {"tick_lower": 20820, "tick_upper": 34680, "liquidity": 193758518324250673152, "amount_token1": 500.0}, {"tick_lower": 19440, "tick_upper": 34980, "liquidity": 177184678920180072448, "amount_token1": 500.0}, {"tick_lower": 17940, "tick_upper": 35280, "liquidity": 163149006727845216256, "amount_token1": 500.0}, {"tick_lower": 16080, "tick_upper": 35580, "liquidity": 149994160222475288576, "amount_token1": 500.0}, {"tick_lower": 13860, "tick_upper": 35820, "liquidity": 138562844580541890560, "amount_token1": 500.0}, {"tick_lower": 10980, "tick_upper": 36120, "liquidity": 127346331288581505024, "amount_token1": 500.0}, {"tick_lower": 6960, "tick_upper": 36360, "liquidity": 116801508777613017088, "amount_token1": 500.0}, {"tick_lower": 0, "tick_upper": 36660, "liquidity": 105367021060013277184, "amount_token1": 500.0}, {"tick_lower": -4800, "tick_upper": 36900, "liquidity": 100063307223705075712, "amount_token1": 500.0}]}}